{
	"name": "ds_generic_adls_parquet",
	"properties": {
		"linkedServiceName": {
			"referenceName": "ls_adls_rcm_dev",
			"type": "LinkedServiceReference"
		},
		"parameters": {
			"container": {
				"type": "string"
			},
			"file_path": {
				"type": "string"
			},
			"file_name": {
				"type": "string"
			}
		},
		"annotations": [],
		"type": "Parquet",
		"typeProperties": {
			"location": {
				"type": "AzureBlobFSLocation",
				"fileName": "@dataset().file_name",
				"folderPath": "@dataset().file_path",
				"fileSystem": "@dataset().container"
			},
			"compressionCodec": "snappy"
		},
		"schema": []
	}
}